quackpipe/__init__.py
quackpipe/builder.py
quackpipe/cli.py
quackpipe/config.py
quackpipe/config.schema.yml
quackpipe/core.py
quackpipe/etl_utils.py
quackpipe/exceptions.py
quackpipe/secrets.py
quackpipe/utils.py
quackpipe/commands/__init__.py
quackpipe/commands/common.py
quackpipe/commands/generate_sqlmesh_config.py
quackpipe/commands/preview_config.py
quackpipe/commands/ui.py
quackpipe/commands/validate.py
quackpipe/sources/__init__.py
quackpipe/sources/azure_blob.py
quackpipe/sources/base.py
quackpipe/sources/mysql.py
quackpipe/sources/postgres.py
quackpipe/sources/s3.py
quackpipe/sources/sqlite.py
quackpipe/sources/ducklake/__init__.py
quackpipe/sources/ducklake/providers.py
quackpipe/test_utils/__init__.py
quackpipe/test_utils/azurite_fixtures.py
quackpipe/test_utils/data_generators.py
quackpipe/test_utils/ducklake_fixtures.py
quackpipe/test_utils/fixtures.py
quackpipe/test_utils/minio_fixtures.py
quackpipe/test_utils/mysql_fixtures.py
quackpipe/test_utils/postgres_fixtures.py
quackpipe-0.7.0.dist-info/licenses/LICENSE
quackpipe-0.7.0.dist-info/METADATA
quackpipe-0.7.0.dist-info/WHEEL
quackpipe-0.7.0.dist-info/entry_points.txt
quackpipe-0.7.0.dist-info/top_level.txt
quackpipe-0.7.0.dist-info/RECORD
