Metadata-Version: 2.4
Name: quackpipe
Version: 0.7.0
Summary: A configuration-driven and programmatic ETL helper for DuckDB.
License: MIT
Requires-Python: >=3.12
License-File: LICENSE
Requires-Dist: pyyaml
Requires-Dist: jsonschema
Requires-Dist: duckdb>=0.9.0
Requires-Dist: pandas
Requires-Dist: python-dotenv
Provides-Extra: dev
Requires-Dist: pytest; extra == "dev"
Requires-Dist: pytest-cov; extra == "dev"
Requires-Dist: quackpipe[fixtures]; extra == "dev"
Requires-Dist: ipdb; extra == "dev"
Provides-Extra: fixtures
Requires-Dist: testcontainers[azurite,minio,mysql,postgres]==4.12.0; extra == "fixtures"
Requires-Dist: sqlalchemy; extra == "fixtures"
Requires-Dist: psycopg2-binary; extra == "fixtures"
Requires-Dist: httpx; extra == "fixtures"
Provides-Extra: lint
Requires-Dist: ruff; extra == "lint"
Provides-Extra: logging
Requires-Dist: structlog>=23.0.0; extra == "logging"
Requires-Dist: colorlog>=6.0.0; extra == "logging"
Provides-Extra: postgres
Requires-Dist: psycopg; extra == "postgres"
Provides-Extra: mysql
Requires-Dist: mysql-connector-python; extra == "mysql"
Provides-Extra: s3
Requires-Dist: pyarrow; extra == "s3"
Provides-Extra: kafka
Requires-Dist: confluent-kafka; extra == "kafka"
Dynamic: license-file
